{
  "collectionName": "components_blocks_featured_news",
  "info": {
    "displayName": "Featured News"
  },
  "options": {},
  "attributes": {
    "newsPosts": {
      "type": "relation",
      "relation": "oneToMany",
      "target": "api::news-post.news-post"
    },
    "heading": {
      "type": "component",
      "component": "shared.heading-large",
      "repeatable": false
    },
    "colorBackground": {
      "type": "enumeration",
      "default": "TRANSPARENT",
      "enum": [
        "TRANSPARENT",
        "WHITE",
        "BLACK",
        "PRIMARY",
        "PRIMARY-HALF",
        "SECONDARY",
        "SECONDARY-HALF",
        "BG-PRIMARY",
        "BG-SECONDARY",
        "GRAY",
        "GRAY-DARK"
      ]
    },
    "cta": {
      "type": "component",
      "component": "shared.link",
      "repeatable": false
    },
    "postBackground": {
      "type": "enumeration",
      "default": "TRANSPARENT",
      "enum": [
        "TRANSPARENT",
        "WHITE",
        "BLACK",
        "PRIMARY",
        "PRIMARY-HALF",
        "SECONDARY",
        "SECONDARY-HALF",
        "BG-PRIMARY",
        "BG-SECONDARY",
        "GRAY",
        "GRAY-DARK"
      ]
    }
  },
  "config": {}
}
