{
  "collectionName": "components_blocks_featured_partners",
  "info": {
    "displayName": "Featured Partners"
  },
  "options": {},
  "attributes": {
    "title": {
      "type": "string"
    },
    "description": {
      "type": "text"
    },
    "partners": {
      "type": "component",
      "component": "shared.logo-link",
      "repeatable": true
    },
    "heading": {
      "type": "component",
      "component": "shared.heading-large",
      "repeatable": false
    },
    "colorBackground": {
      "type": "enumeration",
      "default": "TRANSPARENT",
      "enum": [
        "TRANSPARENT",
        "WHITE",
        "BLACK",
        "PRIMARY",
        "PRIMARY-HALF",
        "SECONDARY",
        "SECONDARY-HALF",
        "BG-PRIMARY",
        "BG-SECONDARY",
        "GRAY",
        "GRAY-DARK"
      ]
    },
    "cta": {
      "type": "component",
      "component": "shared.link",
      "repeatable": false
    }
  },
  "config": {}
}
